setup.cfg
setup.py
morse_talk/__init__.py
morse_talk/decoding.py
morse_talk/encoding.py
morse_talk.egg-info/PKG-INFO
morse_talk.egg-info/SOURCES.txt
morse_talk.egg-info/dependency_links.txt
morse_talk.egg-info/top_level.txt