Metadata-Version: 1.1
Name: morse-talk
Version: 0.1.1
Summary: An aide to Morse Code
Home-page: https://github.com/orkohunter/morse-talk
Author: Himanshu Mishra
Author-email: himanshu2014iit@gmail.com
License: MIT
Download-URL: https://github.com/orkohunter/morse-talk/tarball/v0.1
Keywords: morse code talk
Platform: UNKNOWN
Classifier: Development Status :: 4 - Beta
Classifier: Programming Language :: Python :: 2
Classifier: Programming Language :: Python :: 3
